inputexec/__init__.py
inputexec/cli.py
inputexec/compat.py
inputexec/config.py
inputexec/events.py
inputexec/executors.py
inputexec/loop.py
inputexec/readers/__init__.py
inputexec/readers/base.py
inputexec/readers/evdev.py
inputexec/readers/line.py
inputexec-0.2.5.data/scripts/inputexec
inputexec-0.2.5.dist-info/METADATA
inputexec-0.2.5.dist-info/WHEEL
inputexec-0.2.5.dist-info/top_level.txt
inputexec-0.2.5.dist-info/RECORD
